agentify/__init__.py
agentify/_cli.py
agentify/agentify.py
agentify/agents.py
agentify/cli.py
agentify/cli_config.py
agentify/cli_ui.py
agentify/runtime_client.py
agentify/server.py
agentify/specs.py
agentify/tool.py
agentify/tools.py
agentify/commands/__init__.py
agentify/commands/agent.py
agentify/commands/config.py
agentify/commands/deploy.py
agentify/commands/gateway.py
agentify/commands/provider.py
agentify/commands/run.py
agentify/commands/runtime.py
agentify/commands/serve.py
agentify/commands/tool.py
agentify/gateway/server.py
agentify/providers/__init__.py
agentify/providers/agentify.py
agentify/providers/anthropic.py
agentify/providers/backplane.py
agentify/providers/bedrock.py
agentify/providers/deepseek.py
agentify/providers/github.py
agentify/providers/google.py
agentify/providers/mistral.py
agentify/providers/ollama.py
agentify/providers/ollama_local.py
agentify/providers/openai.py
agentify/providers/x.py
agentify/runtime/__init__.py
agentify/runtime/server.py
agentify/ui/agent_list.css
agentify/ui/agent_list.html
agentify/ui/basic-chat.css
agentify/ui/chat.css
agentify/ui/chat.html
agentify/ui/fun_agent_list.html
agentify/ui/htmx.min.js
agentify/ui/retro-chat.css
agentify/ui/runtime_chat.html
agentify/utils/env_manager.py
agentify_toolkit-0.16.0.dist-info/licenses/LICENSE
agentify_toolkit-0.16.0.dist-info/licenses/NOTICE
agentify_toolkit-0.16.0.dist-info/METADATA
agentify_toolkit-0.16.0.dist-info/WHEEL
agentify_toolkit-0.16.0.dist-info/entry_points.txt
agentify_toolkit-0.16.0.dist-info/top_level.txt
agentify_toolkit-0.16.0.dist-info/RECORD
