Metadata-Version: 2.4
Name: agentify_toolkit
Version: 0.16.0
Summary: Python Toolkit for Declarative AI Agent Development
Author-email: Lewis Sheridan <lewis@backplane.dev>
License:                                  Apache License
Project-URL: Homepage, https://github.com/backplane-cloud/agentify-toolkit
Project-URL: Issues, https://github.com/backplane-cloud/agentify-toolkit/issues
Keywords: ai,agents,llm,openai,anthropic,bedrock
Classifier: License :: OSI Approved :: Apache Software License
Classifier: Programming Language :: Python :: 3.10
Classifier: Development Status :: 3 - Alpha
Classifier: Intended Audience :: Developers
Requires-Python: >=3.10
License-File: LICENSE
License-File: NOTICE
Requires-Dist: pyyaml>=6.0
Requires-Dist: rich>=13.0
Requires-Dist: click>=8.1
Requires-Dist: openai>=1.0
Requires-Dist: anthropic>=0.25
Requires-Dist: boto3>=1.34
Requires-Dist: xai_sdk>=1.5.0
Requires-Dist: google-genai>=0.8
Requires-Dist: fastapi<1.0.0,>=0.128.0
Requires-Dist: uvicorn>=0.26
Requires-Dist: python-multipart>=0.0.6
Requires-Dist: mistralai>=1.0.0
Requires-Dist: ollama>=0.6.1
Requires-Dist: python-dotenv>=1.2.1
Dynamic: license-file
